sealium/__init__.py
sealium/utils/crypto/__init__.py
sealium/utils/crypto/asymmetric.py
sealium/utils/crypto/semmetric.py
sealium/utils/fetch/__init__.py
sealium/utils/fetch/hardwaredata.py
sealium-0.0.2.dist-info/licenses/LICENSE
sealium-0.0.2.dist-info/METADATA
sealium-0.0.2.dist-info/WHEEL
sealium-0.0.2.dist-info/top_level.txt
sealium-0.0.2.dist-info/RECORD
