Metadata-Version: 2.4
Name: sealium
Version: 0.0.2
Summary: Sealium is a state-of-the-art Python library for secure licensing and activation management.
Author: Kevin Hsu
License-Expression: GPL-3.0-or-later
License-File: LICENSE
Requires-Dist: cryptography
Dynamic: license-file
